nwpc_workflow_model/__init__.py
nwpc_workflow_model/bunch.py
nwpc_workflow_model/node.py
nwpc_workflow_model/node_status.py
nwpc_workflow_model/node_type.py
nwpc_workflow_model/node_variable.py
nwpc_workflow_model/visitor.py
nwpc_workflow_model/workflow_node.py
nwpc_workflow_model/ecflow/__init__.py
nwpc_workflow_model/ecflow/bunch.py
nwpc_workflow_model/ecflow/ecflow_node.py
nwpc_workflow_model/ecflow/node.py
nwpc_workflow_model/sms/__init__.py
nwpc_workflow_model/sms/bunch.py
nwpc_workflow_model/sms/node.py
nwpc_workflow_model/sms/sms_node.py
nwpc_workflow_model/sms/sms_status_analyzer.py
tests/ecflow/__init__.py
tests/ecflow/test_bunch.py
tests/ecflow/test_ecflow_node.py
tests/ecflow/test_node.py
tests/node_status/__init__.py
tests/node_status/test_ecflow_node_status.py
tests/node_status/test_sms_node_status.py
tests/sms/__init__.py
tests/sms/test_bunch.py
tests/sms/test_node.py
tests/sms/test_sms_node.py
tests/sms/test_sms_status_analyzer.py
tests/sms/test_visitor.py
nwpc_workflow_model-0.3.0.dist-info/LICENSE
nwpc_workflow_model-0.3.0.dist-info/METADATA
nwpc_workflow_model-0.3.0.dist-info/WHEEL
nwpc_workflow_model-0.3.0.dist-info/top_level.txt
nwpc_workflow_model-0.3.0.dist-info/RECORD
