Metadata-Version: 2.1
Name: nwpc-workflow-model
Version: 0.3.0
Summary: A workflow model using in operation systems at NWPC.
Home-page: https://github.com/perillaroc/nwpc-workflow-model
Author: perillaroc
Author-email: perillaroc@gmail.com
License: MIT
Keywords: nwpc workflow model
Platform: UNKNOWN
Classifier: Development Status :: 2 - Pre-Alpha
Classifier: Intended Audience :: Developers
Classifier: License :: OSI Approved :: MIT License
Classifier: Programming Language :: Python :: 3.6
Classifier: Programming Language :: Python :: 3.7
Provides-Extra: cov
Requires-Dist: pytest-cov ; extra == 'cov'
Requires-Dist: codecov ; extra == 'cov'
Provides-Extra: test
Requires-Dist: pytest ; extra == 'test'
